miniroute/__init__.py
miniroute/examples/basic_get.py
miniroute/examples/binding.py
miniroute/miniroute.py
miniroute-0.2.5.dist-info/LICENCE
miniroute-0.2.5.dist-info/METADATA
miniroute-0.2.5.dist-info/WHEEL
miniroute-0.2.5.dist-info/entry_points.txt
miniroute-0.2.5.dist-info/RECORD
