Metadata-Version: 2.3
Name: miniroute
Version: 0.2.5
Summary: A minimal HTTP routing framework based on Python’s built-in `http.server` for IPC tooling.
License: PSF
Author: Léo Hehlen
Author-email: leo.hehlen@gmail.com
Requires-Python: >=3.11
Classifier: License :: Other/Proprietary License
Classifier: Programming Language :: Python :: 3
Classifier: Programming Language :: Python :: 3.11
Classifier: Programming Language :: Python :: 3.12
Classifier: Programming Language :: Python :: 3.13
